{
    "name": "Semantic versions",
    "description": {
        "short": "Identify the later semantic version number.",
        "full": "[Semantic versioning](https://nodesource.com/blog/semver-a-primer/#semverconstruction) is a popular standard for tracking software versions, and has a strict interpetation for each of the numbers in the version string. Write a function that determines which of two semantic version numbers refer to the later release."
    },

    "added_by": {
        "name": "anyweez",
        "url": "https://github.com/anyweez"
    },
    "added_on": "2016-09-14",
    "status": {
        "available": true
    },

    "spec": {
        "func": "semver",
        "parameters": ["string", "string"],
        "returns": "string",
        "examples": [{
            "inputs": ["1.2.0", "1.12.0"],
            "output": "1.12.0"
        },{
            "inputs": ["1.2.0", "1.2.1"],
            "output": "1.2.1"
        },{
            "inputs": ["11.2.1", "2.1.10"],
            "output": "11.2.1"
        }]
    },
    
    "tests": "semver.js"
}